[ 
    {
      "matchId": "1",
      "teamA": "Appleby Arrows",
      "imageA": "/images/Appleby_Arrows.jpeg",
      "teamB":"Avispas de Wimbourne",
      "imageB": "/images/Avispas_Wimbourne.jpeg",
      "scoreA": 10,
      "scoreB": 60,
      "location": "Campo de Quidditch de Hogwarts",
      "date": "2024-09-14",
      "highlights": [
        {
          "time": "13:31",
          "description": "Appleby Arrows"
        },
        {
          "time": "08:15",
          "description": "Avispas de Wimbourne toma la delantera con una quaffle"
        }
      ],
      "odds": { "teamA": 3.5, "teamB": 1.4, "draw": 2 }
    },
    {
      "matchId": "2",
      "teamA": "Gryffindor",
      "imageA": "/images/Gryffindor.jpeg",
      "teamB": "Slytherin",
      "imageB": "/images/Slytherin.jpeg",
      "scoreA": 150,
      "scoreB": 120,
      "location": "Campo de Quidditch de Hogwarts",
      "date": "2024-09-10",
      "event": "Copa de Hogwarts",
      "highlights": [
        {
          "time": "15:32",
          "description": "Gran atrapada de la snitch por Gryffindor"
        },
        {
          "time": "05:14",
          "description": "Slytherin toma la delantera con una quaffle"
        }
      ],
      "odds": { "teamA": 3.5, "teamB": 1.4, "draw": 2 }
    },
    {
      "id": 3,
      "teamA" : "Argentina",
      "imageA": "/images/Argentina.jpeg",
      "teamB": "Brasil",
      "imageB": "/images/Brasil.jpeg",
      "scoreA": 180,
      "scoreB": 220,
      "location": "Campo de Quidditch de Maré Alta",
      "date": "2024-09-01",
      "highlights": [
        {
          "time": "15:32",
          "description": "Gran jugada de anotación por parte de Argentina"
        },
        {
          "time": "05:14",
          "description": "Brasil toma la delantera con una quaffle"
        }
      ],
      "odds": { "teamA": 3.5, "teamB": 1.4, "draw": 2 }
    },
    {
      "id": 4,
      "teamA": {
        "name": "Perú",
        "image": "/images/Peru.jpeg"
      },
      "teamB": {
        "name": "Brasil",
        "image": "/images/Brasil.jpeg"
      },
      "scoreA": 20,
      "scoreB": 40,
      "location": "Campo de Quidditch de Maré Alta",
      "date": "2024-09-03",
      "highlights": [
        {
          "time": "15:32",
          "description": "Gran jugada de anotación por parte de Perú"
        },
        {
          "time": "05:14",
          "description": "Brasil toma la delantera con una quaffle"
        }
      ],
      "odds": { "teamA": 3.5, "teamB": 1.4, "draw": 2 }
    },
    {
      "id": 5,
      "teamA": {
        "name": "Irlanda",
        "image": "/images/Irlanda.jpeg"
      },
      "teamB": {
        "name": "Nueva Zelanda",
        "image": "/images/Nueva_Zelanda.jpeg"
      },
      "scoreA": 160,
      "scoreB": 100,
      "location": "Campo de Quidditch de Tara",
      "date": "2024-09-11",
      "highlights": [
        {
          "time": "15:32",
          "description": "Gran jugada de anotación por parte de Irlanda"
        },
        {
          "time": "05:14",
          "description": "Nueva Zelanda toma la delantera con una quaffle"
        }
      ],
      "odds": { "teamA": 3.5, "teamB": 1.4, "draw": 2 }
    },
    {
      "id": 6,
      "teamA": {
        "name": "Hufflepuff",
        "image": "/images/Hufflepuff.jpeg"
      },
      "teamB": {
        "name": "Ravenclaw",
        "image": "/images/Ravenclaw.jpeg"
      },
      "scoreA": 100,
      "scoreB": 90,
      "location": "Campo de Quidditch de Hogwarts",
      "date": "2024-09-11",
      "highlights": [
        {
          "time": "10:12",
          "description": "Ravenclaw anotó con una jugada rápida"
        },
        {
          "time": "20:05",
          "description": "Hufflepuff iguala el marcador con un golpe limpio"
        }
      ],
      "odds": { "teamA": 3.5, "teamB": 1.4, "draw": 2 }
    },
    {
      "id": 7,
      "teamA": {
        "name": "Gryffindor",
        "image": "/images/Gryffindor.jpeg"
      },
      "teamB": {
        "name": "Hufflepuff",
        "image": "/images/Hufflepuff.jpeg"
      },
      "scoreA": 200,
      "scoreB": 90,
      "location": "Campo de Quidditch de Hogwarts",
      "date": "2024-09-16",
      "highlights": [
        {
          "time": "10:12",
          "description": "Hufflepuff anotó con una jugada rápida"
        },
        {
          "time": "20:05",
          "description": "Gryffindor iguala el marcador con un golpe limpio"
        }
      ],
      "odds": { "teamA": 3.5, "teamB": 1.4, "draw": 2 }
    }
  ]
  
  